gwcmodel/__init__.py
gwcmodel/gwc.py
gwcmodel-0.1.1.dist-info/METADATA
gwcmodel-0.1.1.dist-info/WHEEL
gwcmodel-0.1.1.dist-info/top_level.txt
gwcmodel-0.1.1.dist-info/RECORD
